LICENSE.md
README.md
setup.py
app_common/__init__.py
app_common.egg-info/PKG-INFO
app_common.egg-info/SOURCES.txt
app_common.egg-info/dependency_links.txt
app_common.egg-info/requires.txt
app_common.egg-info/top_level.txt
app_common.egg-info/zip-safe
app_common/cf_xml_reader/__init__.py
app_common/cf_xml_reader/cf-standard-name-table.xml
app_common/cf_xml_reader/cf_xml_reader.py
app_common/config/__init__.py
app_common/config/config_handler.py
app_common/config/template/__init__.py
app_common/config/template/default_django_setting.yml-tpl
app_common/config/template/default_setting.yml-tpl
app_common/custom_mysql/__init__.py
app_common/custom_mysql/custom_mysql.py
app_common/erddapy_proxy/__init__.py
app_common/erddapy_proxy/erddapy_proxy.py
app_common/errdap_dataset_configuration_editor/__init__.py
app_common/errdap_dataset_configuration_editor/dataset_xml_editor.py
app_common/errdap_dataset_configuration_editor/dataset_xml_editor_base.py
app_common/errdap_dataset_configuration_editor/erddap_dataset_configure_parser.py
app_common/linux_file_handler/__init__.py
app_common/linux_file_handler/file_system_controller.py
app_common/linux_file_handler/file_system_manager.py
app_common/linux_file_handler/linux_command.py
app_common/linux_file_handler/loacl_command_executor.py
app_common/linux_file_handler/remote_server_connector.py
app_common/linux_file_handler/utils.py
app_common/sensor_tracker_proxy/__init__.py
app_common/sensor_tracker_proxy/sensor_tracker_proxy.py
app_common/slack_message/__init__.py
app_common/slack_message/slack_message.py
app_common/test_common/__init__.py
app_common/test_common/base.py
app_common/test_common/testserver/__init__.py
app_common/test_common/testserver/server.py
app_common/utilities/__init__.py
app_common/utilities/dataset_id_generate_function.py
app_common/utilities/file_prepare.py
app_common/utilities/gps_points_tools.py
app_common/utilities/list_compare.py
app_common/utilities/os_function.py
app_common/utilities/string_tools.py
app_common/utilities/time_format_functions.py
app_common/utilities/nc-reader/__init__.py
app_common/utilities/nc-reader/nc-reader.py
test/__init__.py
test/ceotr_django/__init__.py
